consolechess/.DS_Store
consolechess/__init__.py
consolechess/__main__.py
consolechess/asciiconsole.py
consolechess/atomic.py
consolechess/board.cpython-310-darwin.so
consolechess/board.cpython-311-darwin.so
consolechess/board.cpython-312-darwin.so
consolechess/board.py
consolechess/board__mypyc.cpython-310-darwin.so
consolechess/board__mypyc.cpython-311-darwin.so
consolechess/board__mypyc.cpython-312-darwin.so
consolechess/console.py
consolechess/crazyhouse.py
consolechess/fischer_setups.json
consolechess/horde.py
consolechess/king_of_the_hill.py
consolechess/openings.json
consolechess/py.typed
consolechess/styles.css
consolechess/three_check.py
consolechess/tui.py
consolechess/utils.py
consolechess-0.2.92.dist-info/METADATA
consolechess-0.2.92.dist-info/WHEEL
consolechess-0.2.92.dist-info/entry_points.txt
consolechess-0.2.92.dist-info/RECORD
